pixel_patrol_base/__init__.py
pixel_patrol_base/api.py
pixel_patrol_base/cli.py
pixel_patrol_base/config.py
pixel_patrol_base/plugin_registry.py
pixel_patrol_base/core/__init__.py
pixel_patrol_base/core/contracts.py
pixel_patrol_base/core/feature_schema.py
pixel_patrol_base/core/file_system.py
pixel_patrol_base/core/processing.py
pixel_patrol_base/core/project.py
pixel_patrol_base/core/project_settings.py
pixel_patrol_base/core/record.py
pixel_patrol_base/core/specs.py
pixel_patrol_base/core/validation.py
pixel_patrol_base/io/project_io.py
pixel_patrol_base/plugins/__init__.py
pixel_patrol_base/plugins/processors/__init__.py
pixel_patrol_base/plugins/processors/basic_stats_processor.py
pixel_patrol_base/plugins/processors/histogram_processor.py
pixel_patrol_base/plugins/processors/thumbnail_processor.py
pixel_patrol_base/plugins/widgets/__init__.py
pixel_patrol_base/plugins/widgets/base_dynamic_table_widget.py
pixel_patrol_base/plugins/widgets/dataset_stats/__init__.py
pixel_patrol_base/plugins/widgets/dataset_stats/dataset_histograms.py
pixel_patrol_base/plugins/widgets/dataset_stats/dataset_stats.py
pixel_patrol_base/plugins/widgets/dataset_stats/dynamic_dataset_metrics.py
pixel_patrol_base/plugins/widgets/file_stats/__init__.py
pixel_patrol_base/plugins/widgets/file_stats/file_stats.py
pixel_patrol_base/plugins/widgets/metadata/__init__.py
pixel_patrol_base/plugins/widgets/metadata/data_type.py
pixel_patrol_base/plugins/widgets/metadata/dim_order.py
pixel_patrol_base/plugins/widgets/metadata/dim_size.py
pixel_patrol_base/plugins/widgets/summary/__init__.py
pixel_patrol_base/plugins/widgets/summary/dataframe.py
pixel_patrol_base/plugins/widgets/summary/file_summary.py
pixel_patrol_base/plugins/widgets/summary/sunburst.py
pixel_patrol_base/plugins/widgets/visualization/__init__.py
pixel_patrol_base/plugins/widgets/visualization/embedding_projector.py
pixel_patrol_base/plugins/widgets/visualization/image_mosaik.py
pixel_patrol_base/report/__init__.py
pixel_patrol_base-0.1.2.dist-info/METADATA
pixel_patrol_base-0.1.2.dist-info/WHEEL
pixel_patrol_base-0.1.2.dist-info/entry_points.txt
pixel_patrol_base-0.1.2.dist-info/top_level.txt
pixel_patrol_base-0.1.2.dist-info/RECORD
